PokerBots/__init__.py
PokerBots/game/Game.py
PokerBots/game/__init__.py
PokerBots/players/BasePlayer.py
PokerBots/players/CallingPlayer.py
PokerBots/players/GamblingPlayer.py
PokerBots/players/RandomPlayer.py
PokerBots/players/__init__.py
PokerBots-2.0.6.dist-info/LICENSE
PokerBots-2.0.6.dist-info/METADATA
PokerBots-2.0.6.dist-info/WHEEL
PokerBots-2.0.6.dist-info/top_level.txt
PokerBots-2.0.6.dist-info/RECORD
