Metadata-Version: 2.1
Name: PokerBots
Version: 2.0.6
Summary: A Pure Python library to test your Poker Bots in a trivial and simple way.
Home-page: https://github.com/Skripkon/PokerBots
Author: Nikolay Skripko
Author-email: nskripko@icloud.com
License: MIT
Classifier: Development Status :: 4 - Beta
Classifier: Intended Audience :: Developers
Classifier: License :: OSI Approved :: MIT License
Classifier: Programming Language :: Python :: 3
Requires-Python: >=3.11
License-File: LICENSE
Requires-Dist: pokerkit==0.5.4
Requires-Dist: treys==0.1.8
